task_manager/__about__.py
task_manager/__init__.py
task_manager/admin.py
task_manager/apps.py
task_manager/models.py
task_manager/settings.py
task_manager/core/actions.py
task_manager/core/constants.py
task_manager/core/decorators.py
task_manager/core/exceptions.py
task_manager/core/settings.py
task_manager/core/signals.py
task_manager/core/types.py
task_manager/core/pytest/__init__.py
task_manager/core/pytest/fixtures/__init__.py
task_manager/core/pytest/fixtures/dont_wait_for_rescheduling_tasks.py
task_manager/django/__init__.py
task_manager/django/actions.py
task_manager/django/admin.py
task_manager/django/decorators.py
task_manager/django/dispatch.py
task_manager/django/models.py
task_manager/django/receivers.py
task_manager/django/tasks.py
task_manager/management/__init__.py
task_manager/management/commands/__init__.py
task_manager/management/commands/task_manager.py
task_manager/migrations/0001_initial.py
task_manager/migrations/0002_scheduledtask.py
task_manager/migrations/0003_taskmanager_fixed.py
task_manager/migrations/0004_signalerror.py
task_manager/migrations/0005_taskmanager_priority.py
task_manager/migrations/__init__.py
task_manager/pytest/__init__.py
task_manager/pytest/core/__init__.py
task_manager/pytest/core/fixtures/__init__.py
task_manager/pytest/core/fixtures/dont_wait_for_rescheduling_tasks.py
task_manager/templates/task_manager_report.html
task_manager/templates/task_manager_report.txt
celery_task_manager-1.11.4.dist-info/METADATA
celery_task_manager-1.11.4.dist-info/WHEEL
celery_task_manager-1.11.4.dist-info/licenses/LICENSE.txt
celery_task_manager-1.11.4.dist-info/RECORD
