Metadata-Version: 2.4
Name: celery-task-manager
Version: 1.11.4
Project-URL: Documentation, https://breatheco-de.github.io/celery-task-manager-django-plugin/
Project-URL: Issues, https://github.com/breatheco-de/celery-task-manager-django-plugin/issues
Project-URL: Source, https://github.com/breatheco-de/celery-task-manager-django-plugin
Author-email: jefer94 <jdefreitaspinto@gmail.com>
License-Expression: LGPL-3.0-or-later
License-File: LICENSE.txt
Classifier: Development Status :: 5 - Production/Stable
Classifier: Framework :: Django :: 4.2
Classifier: Framework :: Django :: 5.0
Classifier: License :: OSI Approved :: GNU Lesser General Public License v3 or later (LGPLv3+)
Classifier: Programming Language :: Python
Classifier: Programming Language :: Python :: 3.10
Classifier: Programming Language :: Python :: 3.11
Classifier: Programming Language :: Python :: 3.12
Classifier: Programming Language :: Python :: Implementation :: CPython
Classifier: Programming Language :: Python :: Implementation :: PyPy
Classifier: Topic :: Software Development :: Libraries
Requires-Python: >=3.11
Requires-Dist: celery
Provides-Extra: circuitbreaker
Requires-Dist: circuitbreaker; extra == 'circuitbreaker'
Provides-Extra: django
Requires-Dist: django; extra == 'django'
